capi/__init__.py
capi/containers/__init__.py
capi/containers/mapping/__init__.py
capi/containers/mapping/frozendict.py
capi/tools/__init__.py
capi/tools/hashing.py
commonapi-0.0.1.dist-info/LICENSE
commonapi-0.0.1.dist-info/METADATA
commonapi-0.0.1.dist-info/WHEEL
commonapi-0.0.1.dist-info/top_level.txt
commonapi-0.0.1.dist-info/RECORD
